{
  "BattleStatuses": {
    "2xthetap": {
      "noCopy": true
    },
    "5gen": {
      "noCopy": true
    },
    "acakewearingahat": {
      "noCopy": true,
      "onModifyDefPriority": 6,
      "onModifySpDPriority": 6
    },
    "aelita": {
      "noCopy": true
    },
    "akir": {
      "noCopy": true
    },
    "amaluna": {
      "noCopy": true
    },
    "andy": {
      "noCopy": true
    },
    "ant": {
      "noCopy": true
    },
    "aquagtothepast": {
      "noCopy": true
    },
    "arcticblast": {
      "noCopy": true
    },
    "arrested": {
      "noCopy": true
    },
    "arsenal": {
      "noCopy": true
    },
    "beowulf": {
      "noCopy": true
    },
    "bhrisbrown": {
      "noCopy": true
    },
    "biggie": {
      "noCopy": true
    },
    "bimp": {
      "noCopy": true
    },
    "bobochan": {
      "noCopy": true
    },
    "brandon": {
      "noCopy": true
    },
    "bumbadadabum": {
      "noCopy": true
    },
    "cantsay": {
      "noCopy": true
    },
    "cc": {
      "noCopy": true
    },
    "cerberax": {
      "noCopy": true
    },
    "ceteris": {
      "noCopy": true
    },
    "chaos": {
      "noCopy": true
    },
    "chloe": {
      "noCopy": true
    },
    "cleo": {
      "noCopy": true
    },
    "deg": {
      "noCopy": true
    },
    "dragonwhale": {
      "noCopy": true
    },
    "duck": {
      "noCopy": true
    },
    "e4flint": {
      "noCopy": true
    },
    "earthboundmisfit": {
      "noCopy": true
    },
    "explodingdaisies": {
      "noCopy": true
    },
    "eien": {
      "noCopy": true
    },
    "eternally": {
      "noCopy": true
    },
    "ev": {
      "noCopy": true
    },
    "false": {
      "noCopy": true
    },
    "fomg": {
      "noCopy": true
    },
    "kalalokki": {
      "noCopy": true
    },
    "grimauxiliatrix": {
      "noCopy": true
    },
    "hippopotasuser": {
      "noCopy": true
    },
    "hipstersigilyph": {
      "noCopy": true
    },
    "hoeenhero": {
      "noCopy": true
    },
    "hubriz": {
      "noCopy": true
    },
    "hurl": {
      "noCopy": true
    },
    "imagi": {
      "noCopy": true
    },
    "imas": {
      "noCopy": true
    },
    "iyarito": {
      "noCopy": true
    },
    "jdarden": {
      "noCopy": true
    },
    "kaijubunny": {
      "noCopy": true
    },
    "kay": {
      "noCopy": true
    },
    "kingswordyt": {
      "noCopy": true
    },
    "level51": {
      "noCopy": true
    },
    "lifeisdank": {
      "noCopy": true,
      "onModifyMovePriority": -1,
      "onBasePowerPriority": 8
    },
    "lionyx": {
      "noCopy": true
    },
    "lostseso": {
      "noCopy": true
    },
    "lycaniumz": {
      "noCopy": true
    },
    "macchaeger": {
      "noCopy": true
    },
    "majorbowman": {
      "noCopy": true
    },
    "martha": {
      "noCopy": true
    },
    "marty": {
      "noCopy": true
    },
    "meicoo": {
      "noCopy": true
    },
    "megazard": {
      "noCopy": true
    },
    "mickthespud": {
      "noCopy": true
    },
    "mitsuki": {
      "noCopy": true
    },
    "moo": {
      "noCopy": true
    },
    "morfent": {
      "noCopy": true
    },
    "nui": {
      "noCopy": true
    },
    "om": {
      "noCopy": true
    },
    "osiris": {
      "noCopy": true
    },
    "overneat": {
      "noCopy": true
    },
    "paradise": {
      "noCopy": true
    },
    "pluviometer": {
      "noCopy": true
    },
    "ptoad": {
      "noCopy": true
    },
    "psynergy": {
      "noCopy": true
    },
    "quitequiet": {
      "noCopy": true,
      "onModifyDefPriority": 6,
      "onModifySpDPriority": 6
    },
    "rorymercury": {
      "noCopy": true
    },
    "saburo": {
      "noCopy": true
    },
    "samjo": {
      "noCopy": true
    },
    "scotteh": {
      "noCopy": true
    },
    "shiba": {
      "noCopy": true
    },
    "slowbroth": {
      "noCopy": true
    },
    "snaquaza": {
      "noCopy": true
    },
    "spacebass": {
      "noCopy": true
    },
    "sungodvolcarona": {
      "noCopy": true
    },
    "teclis": {
      "noCopy": true
    },
    "tennisace": {
      "noCopy": true
    },
    "teremiare": {
      "noCopy": true
    },
    "theimmortal": {
      "noCopy": true
    },
    "theleprechaun": {
      "noCopy": true
    },
    "tiksi": {
      "noCopy": true
    },
    "torkool": {
      "noCopy": true
    },
    "trickster": {
      "noCopy": true
    },
    "unleashourpassion": {
      "noCopy": true
    },
    "urkerab": {
      "noCopy": true
    },
    "uselesscrab": {
      "noCopy": true
    },
    "volco": {
      "noCopy": true
    },
    "xayahh": {
      "noCopy": true
    },
    "xprienzo": {
      "noCopy": true
    },
    "yuki": {
      "noCopy": true
    },
    "zarel": {
      "noCopy": true
    },
    "cutietrap": {
      "duration": 5,
      "noCopy": true,
      "onBeforeMovePriority": 2
    },
    "hail": {
      "inherit": true
    },
    "boostreplacement": {
      "name": "boostreplacement",
      "id": "boostreplacement",
      "onSwitchInPriority": 1
    },
    "glitchout": {
      "duration": 1
    },
    "arceus": {
      "inherit": true
    }
  }
}
